geoshort/__init__.py
geoshort/common.py
geoshort/geoshort.py
geoshort-0.0.1.dist-info/LICENSE
geoshort-0.0.1.dist-info/METADATA
geoshort-0.0.1.dist-info/WHEEL
geoshort-0.0.1.dist-info/entry_points.txt
geoshort-0.0.1.dist-info/top_level.txt
geoshort-0.0.1.dist-info/RECORD
